interpolation/__init__.py
interpolation/cartesian.py
interpolation/compat.py
interpolation/complete_poly.py
interpolation/multilinear/__init__.py
interpolation/multilinear/fungen.py
interpolation/multilinear/mlinterp.py
interpolation/multilinear/tests/__init__.py
interpolation/multilinear/tests/test_multilinear.py
interpolation/smolyak/__init__.py
interpolation/smolyak/grid.py
interpolation/smolyak/interp.py
interpolation/smolyak/tests/__init__.py
interpolation/smolyak/tests/test_derivatives.py
interpolation/smolyak/tests/test_interp.py
interpolation/smolyak/util.py
interpolation/splines/__init__.py
interpolation/splines/basis_splines.py
interpolation/splines/codegen.py
interpolation/splines/eval_cubic.py
interpolation/splines/eval_cubic_numba.py
interpolation/splines/eval_splines.py
interpolation/splines/filter_cubic.py
interpolation/splines/hermite.py
interpolation/splines/multilinear.py
interpolation/splines/multilinear_numba.py
interpolation/splines/option_types.py
interpolation/splines/prefilter_cubic.py
interpolation/splines/splines.py
interpolation/splines/tests/__init__.py
interpolation/splines/tests/test_cubic_splines.py
interpolation/splines/tests/test_derivatives.py
interpolation/splines/tests/test_eval_splines.py
interpolation/splines/tests/test_fortran_order.py
interpolation/splines/tests/test_hermite_splines.py
interpolation/splines/tests/test_multilinear_extrap.py
interpolation/splines/tests/test_object_api.py
interpolation/splines/tests/test_readonly.py
interpolation/tempita/__init__.py
interpolation/tempita/_looper.py
interpolation/tempita/compat3.py
interpolation/tests/__init__.py
interpolation/tests/test_complete.py
interpolation/tests/test_derivs.py
interpolation-2.2.6.dist-info/LICENSE
interpolation-2.2.6.dist-info/METADATA
interpolation-2.2.6.dist-info/WHEEL
interpolation-2.2.6.dist-info/RECORD
